remotelab/__init__.py
remotelab/devices.py
remotelab/hal_serial.py
remotelab-0.0.6.dist-info/METADATA
remotelab-0.0.6.dist-info/WHEEL
remotelab-0.0.6.dist-info/top_level.txt
remotelab-0.0.6.dist-info/RECORD
